foebackend/__init__.py
foebackend-1.0.0.dist-info/DESCRIPTION.rst
foebackend-1.0.0.dist-info/METADATA
foebackend-1.0.0.dist-info/RECORD
foebackend-1.0.0.dist-info/WHEEL
foebackend-1.0.0.dist-info/entry_points.txt
foebackend-1.0.0.dist-info/metadata.json
foebackend-1.0.0.dist-info/top_level.txt
